CHANGES.txt
CONTRIBUTORS.txt
COPYRIGHT.txt
LICENSE.txt
MANIFEST.in
README.rst
setup.cfg
setup.py
PyramidZiggurat/__init__.py
PyramidZiggurat.egg-info/PKG-INFO
PyramidZiggurat.egg-info/SOURCES.txt
PyramidZiggurat.egg-info/dependency_links.txt
PyramidZiggurat.egg-info/entry_points.txt
PyramidZiggurat.egg-info/not-zip-safe
PyramidZiggurat.egg-info/requires.txt
PyramidZiggurat.egg-info/top_level.txt
PyramidZiggurat/scaffolds/__init__.py
PyramidZiggurat/scaffolds/ziggurat/CHANGES.txt_tmpl
PyramidZiggurat/scaffolds/ziggurat/MANIFEST.in_tmpl
PyramidZiggurat/scaffolds/ziggurat/README.txt_tmpl
PyramidZiggurat/scaffolds/ziggurat/alembic.ini.tpl
PyramidZiggurat/scaffolds/ziggurat/alembic_upgrade.ini.tpl
PyramidZiggurat/scaffolds/ziggurat/development.ini_tmpl
PyramidZiggurat/scaffolds/ziggurat/message-extraction.ini
PyramidZiggurat/scaffolds/ziggurat/production.ini_tmpl
PyramidZiggurat/scaffolds/ziggurat/setup.cfg_tmpl
PyramidZiggurat/scaffolds/ziggurat/setup.py_tmpl
PyramidZiggurat/scaffolds/ziggurat/+package+/__init__.py_tmpl
PyramidZiggurat/scaffolds/ziggurat/+package+/security.py
PyramidZiggurat/scaffolds/ziggurat/+package+/tests.py_tmpl
PyramidZiggurat/scaffolds/ziggurat/+package+/tools.py
PyramidZiggurat/scaffolds/ziggurat/+package+/locale/+project+.pot
PyramidZiggurat/scaffolds/ziggurat/+package+/models/__init__.py
PyramidZiggurat/scaffolds/ziggurat/+package+/scripts/DbTools.py
PyramidZiggurat/scaffolds/ziggurat/+package+/scripts/__init__.py
PyramidZiggurat/scaffolds/ziggurat/+package+/scripts/initializedb.py
PyramidZiggurat/scaffolds/ziggurat/+package+/scripts/tools.py
PyramidZiggurat/scaffolds/ziggurat/+package+/scripts/data/__init__.py
PyramidZiggurat/scaffolds/ziggurat/+package+/scripts/data/user.py
PyramidZiggurat/scaffolds/ziggurat/+package+/static/css/navbar-fixed-top.css
PyramidZiggurat/scaffolds/ziggurat/+package+/static/css/signin.css
PyramidZiggurat/scaffolds/ziggurat/+package+/static/css/theme.css
PyramidZiggurat/scaffolds/ziggurat/+package+/static/img/favicon.png
PyramidZiggurat/scaffolds/ziggurat/+package+/static/img/pyramid.png
PyramidZiggurat/scaffolds/ziggurat/+package+/views/__init__.py_tmpl
PyramidZiggurat/scaffolds/ziggurat/+package+/views/group.py
PyramidZiggurat/scaffolds/ziggurat/+package+/views/user.py
