Metadata-Version: 1.1
Name: PyramidZiggurat
Version: 0.1.8
Summary: Ziggurat Foundations template for the Pyramid web framework
Home-page: UNKNOWN
Author: Owo Sugiana
Author-email: sugiana@rab.co.id
License: BSD-derived (http://www.repoze.org/LICENSE.txt)
Keywords: web wsgi pylons pyramid
Platform: UNKNOWN
Classifier: Programming Language :: Python
Classifier: Framework :: Pyramid
Classifier: Topic :: Internet :: WWW/HTTP
Classifier: Topic :: Internet :: WWW/HTTP :: WSGI :: Application
